juliandate/__init__.py
juliandate/__version__.py
juliandate/jd.py
juliandate/juliandate.py
juliandate-1.0.4.dist-info/LICENSE
juliandate-1.0.4.dist-info/METADATA
juliandate-1.0.4.dist-info/WHEEL
juliandate-1.0.4.dist-info/entry_points.txt
juliandate-1.0.4.dist-info/top_level.txt
juliandate-1.0.4.dist-info/RECORD
