Metadata-Version: 2.1
Name: juliandate
Version: 1.0.4
Summary: Julian date conversions
Home-page: https://github.com/seanredmond/juliandate
Author: Sean Redmond
Author-email: github-smr@sneakemail.com
Project-URL: Bug Tracker, https://github.com/seanredmond/juliandate/issues
Classifier: Programming Language :: Python :: 3
Classifier: License :: OSI Approved :: GNU General Public License v3 or later (GPLv3+)
Classifier: Operating System :: OS Independent
Requires-Python: >=3.8
License-File: LICENSE
